tests/__init__.py
tests/conftest.py
tests/test_command_line.py
tests/test_components.py
tests/test_config.py
tests/test_multitasking.py
tests/test_platform.py
tests/test_runner.py
tests/test_scanf.py
tests/test_schema.py
tests/test_services.py
tests/test_timing.py
tests/test_tools.py
tests/test_units.py
tests/test_yamlfile.py
tests/communication/__init__.py
tests/communication/test_AsciiFileComm.py
tests/communication/test_AsciiTableComm.py
tests/communication/test_BufferComm.py
tests/communication/test_CommBase.py
tests/communication/test_FileComm.py
tests/communication/test_ForkComm.py
tests/communication/test_IPCComm.py
tests/communication/test_MPIComm.py
tests/communication/test_PandasFileComm.py
tests/communication/test_RESTComm.py
tests/communication/test_RMQAsyncComm.py
tests/communication/test_RMQComm.py
tests/communication/test_ServerComm.py
tests/communication/test_ValueComm.py
tests/communication/test_ZMQComm.py
tests/communication/filters/__init__.py
tests/communication/filters/test_FilterBase.py
tests/communication/transforms/__init__.py
tests/communication/transforms/test_TransformBase.py
tests/demos/__init__.py
tests/demos/test_CiS2021_hackathon.py
tests/demos/test_fspm2020.py
tests/drivers/__init__.py
tests/drivers/test_BuildModelDriver.py
tests/drivers/test_CMakeModelDriver.py
tests/drivers/test_CModelDriver.py
tests/drivers/test_CompiledModelDriver.py
tests/drivers/test_ConnectionDriver.py
tests/drivers/test_Driver.py
tests/drivers/test_ExecutableModelDriver.py
tests/drivers/test_FileInputDriver.py
tests/drivers/test_FileOutputDriver.py
tests/drivers/test_MakeModelDriver.py
tests/drivers/test_MatlabModelDriver.py
tests/drivers/test_ModelDriver.py
tests/drivers/test_RPCRequestDriver.py
tests/examples/__init__.py
tests/examples/test_SaM.py
tests/examples/test_ascii_io.py
tests/examples/test_conditional_io.py
tests/examples/test_gs_lesson4.py
tests/examples/test_model_error_with_io.py
tests/examples/test_rpcFib.py
tests/examples/test_rpc_lesson1.py
yggdrasil_framework-1.8.5.dist-info/LICENSE.txt
yggdrasil_framework-1.8.5.dist-info/METADATA
yggdrasil_framework-1.8.5.dist-info/WHEEL
yggdrasil_framework-1.8.5.dist-info/entry_points.txt
yggdrasil_framework-1.8.5.dist-info/top_level.txt
yggdrasil_framework-1.8.5.dist-info/RECORD
