Metadata-Version: 2.1
Name: yggdrasil-framework
Version: 1.8.5
Summary: A framework for combining interdependent models from multiple languages.
Home-page: https://github.com/cropsinsilico/yggdrasil
Download-URL: https://github.com/cropsinsilico/yggdrasil/archive/v1.8.5.tar.gz
Author: Meagan Lang
Author-email: langmm.astro@gmail.com
License: BSD
Keywords: plants,simulation,models,framework
Classifier: Programming Language :: C
Classifier: Programming Language :: C++
Classifier: Programming Language :: ML
Classifier: Programming Language :: Python
Classifier: Programming Language :: Python :: 3
Classifier: Programming Language :: Python :: 3.5
Classifier: Programming Language :: Python :: 3.6
Classifier: Programming Language :: Python :: 3.7
Classifier: Programming Language :: Python :: 3.8
Classifier: Operating System :: OS Independent
Classifier: Intended Audience :: Science/Research
Classifier: License :: OSI Approved :: BSD License
Classifier: Natural Language :: English
Classifier: Topic :: Scientific/Engineering
Classifier: Development Status :: 5 - Production/Stable
Requires-Python: >=3.5
License-File: LICENSE.txt
Requires-Dist: GitPython
Requires-Dist: chevron
Requires-Dist: flask
Requires-Dist: jsonschema (==3.2.0)
Requires-Dist: matplotlib
Requires-Dist: numpy (>=1.13.0)
Requires-Dist: pandas
Requires-Dist: psutil
Requires-Dist: pyperf
Requires-Dist: python-rapidjson
Requires-Dist: pyyaml
Requires-Dist: pyzmq
Requires-Dist: requests
Requires-Dist: scipy
Requires-Dist: six
Requires-Dist: unyt
Requires-Dist: sysv-ipc ; platform_system != "Windows"
Provides-Extra: astropy
Requires-Dist: astropy ; extra == 'astropy'
Provides-Extra: dev
Requires-Dist: PyGithub ; extra == 'dev'
Requires-Dist: black ; extra == 'dev'
Requires-Dist: ipython ; extra == 'dev'
Requires-Dist: pre-commit ; extra == 'dev'
Provides-Extra: docs
Requires-Dist: breathe ; extra == 'docs'
Requires-Dist: pypandoc ; extra == 'docs'
Requires-Dist: sphinx ; extra == 'docs'
Requires-Dist: sphinx-argparse ; extra == 'docs'
Requires-Dist: sphinx-rtd-theme ; extra == 'docs'
Provides-Extra: mpi
Requires-Dist: mpi4py ; extra == 'mpi'
Provides-Extra: pygments
Requires-Dist: pygments ; extra == 'pygments'
Provides-Extra: rmq
Requires-Dist: pika (>=1.0.0) ; extra == 'rmq'
Provides-Extra: sbml
Requires-Dist: libroadrunner (<2.0.7) ; extra == 'sbml'
Provides-Extra: testing
Requires-Dist: codecov ; extra == 'testing'
Requires-Dist: coverage ; extra == 'testing'
Requires-Dist: flake8 ; extra == 'testing'
Requires-Dist: flaky ; extra == 'testing'
Requires-Dist: pytest ; extra == 'testing'
Requires-Dist: pytest-cov ; extra == 'testing'
Requires-Dist: pytest-drop-dup-tests ; extra == 'testing'
Requires-Dist: pytest-mpi ; extra == 'testing'
Requires-Dist: pytest-repeat ; extra == 'testing'
Requires-Dist: pytest-rerunfailures ; extra == 'testing'
Requires-Dist: pytest-timeout ; extra == 'testing'
Provides-Extra: trimesh
Requires-Dist: trimesh ; extra == 'trimesh'
